minjiang_client/__init__.py
minjiang_client/__main__.py
minjiang_client/auto_cali/__init__.py
minjiang_client/auto_cali/calibration_dag.cpython-312-x86_64-linux-gnu.so
minjiang_client/auto_cali/calibration_dag.pyi
minjiang_client/auto_cali/dag_definition.cpython-312-x86_64-linux-gnu.so
minjiang_client/auto_cali/dag_definition.pyi
minjiang_client/auto_cali/utils.cpython-312-x86_64-linux-gnu.so
minjiang_client/auto_cali/utils.pyi
minjiang_client/com/__init__.py
minjiang_client/com/command.cpython-312-x86_64-linux-gnu.so
minjiang_client/com/command.pyi
minjiang_client/com/device.cpython-312-x86_64-linux-gnu.so
minjiang_client/com/device.pyi
minjiang_client/com/device_client.cpython-312-x86_64-linux-gnu.so
minjiang_client/com/device_client.pyi
minjiang_client/com/file.cpython-312-x86_64-linux-gnu.so
minjiang_client/com/file.pyi
minjiang_client/com/log.cpython-312-x86_64-linux-gnu.so
minjiang_client/com/log.pyi
minjiang_client/com/minio.cpython-312-x86_64-linux-gnu.so
minjiang_client/com/minio.pyi
minjiang_client/com/organization.cpython-312-x86_64-linux-gnu.so
minjiang_client/com/organization.pyi
minjiang_client/com/oss.cpython-312-x86_64-linux-gnu.so
minjiang_client/com/oss.pyi
minjiang_client/com/plugin.cpython-312-x86_64-linux-gnu.so
minjiang_client/com/plugin.pyi
minjiang_client/com/request.cpython-312-x86_64-linux-gnu.so
minjiang_client/com/request.pyi
minjiang_client/com/space.cpython-312-x86_64-linux-gnu.so
minjiang_client/com/space.pyi
minjiang_client/com/sub_process.cpython-312-x86_64-linux-gnu.so
minjiang_client/com/sub_process.pyi
minjiang_client/com/user.cpython-312-x86_64-linux-gnu.so
minjiang_client/com/user.pyi
minjiang_client/compiler/__init__.py
minjiang_client/compiler/gate_compiler.cpython-312-x86_64-linux-gnu.so
minjiang_client/compiler/gate_compiler.pyi
minjiang_client/compiler/gate_compiler_register.cpython-312-x86_64-linux-gnu.so
minjiang_client/compiler/gate_compiler_register.pyi
minjiang_client/doc/__init__.py
minjiang_client-1.1.4.dist-info/METADATA
minjiang_client-1.1.4.dist-info/WHEEL
minjiang_client-1.1.4.dist-info/top_level.txt
minjiang_client-1.1.4.dist-info/RECORD
