Metadata-Version: 2.4
Name: minjiang_client
Version: 1.1.4
Summary: Minjiang pulse-level measurement and control SDK for quantum computing.
Author: ZWDX
Author-email: sales@das-zone.com
License: Apache 2.0
Requires-Python: >=3.7, <4
Requires-Dist: numpy
Requires-Dist: scipy
Requires-Dist: matplotlib
Requires-Dist: msgpack
Requires-Dist: minio
Requires-Dist: psutil
Requires-Dist: uvicorn
Requires-Dist: fastapi
Requires-Dist: requests
Requires-Dist: msgpack-numpy
Requires-Dist: python-multipart
Requires-Dist: scikit-learn
Requires-Dist: portalocker
Requires-Dist: networkx
Requires-Dist: IPython
Requires-Dist: grpcio
Requires-Dist: grpcio-tools
Requires-Dist: ipympl
Requires-Dist: httpx
Requires-Dist: cython>=0.29.0
Dynamic: author
Dynamic: author-email
Dynamic: license
Dynamic: requires-dist
Dynamic: requires-python
Dynamic: summary
